wfetch/__init__.py
wfetch/script.py
wfetch-0.1.2.dist-info/LICENSE
wfetch-0.1.2.dist-info/METADATA
wfetch-0.1.2.dist-info/WHEEL
wfetch-0.1.2.dist-info/entry_points.txt
wfetch-0.1.2.dist-info/top_level.txt
wfetch-0.1.2.dist-info/RECORD
