Metadata-Version: 2.1
Name: wfetch
Version: 0.1.2
Summary: Minimal Windows system information tool written in Python
Home-page: https://github.com/zJairO/wfetch
Author: zJairO
Author-email: hello@zjairo.com
License: UNKNOWN
Project-URL: Bug Tracker, https://github.com/zJairO/wfetch/issues
Platform: UNKNOWN
Classifier: Programming Language :: Python :: 3
Classifier: License :: OSI Approved :: MIT License
Classifier: Operating System :: OS Independent
Requires-Python: >=3.6
License-File: LICENSE
